neat_html/__init__.py
neat_html/compiler.py
neat_html/constants.py
neat_html/tokenizer.py
neat_html/tokens.py
neat_html/types.py
neat_html/utils.py
neat_html-0.6.0.dist-info/LICENSE
neat_html-0.6.0.dist-info/METADATA
neat_html-0.6.0.dist-info/WHEEL
neat_html-0.6.0.dist-info/RECORD
