Metadata-Version: 2.1
Name: neat-html
Version: 0.6.0
Summary: A python library for writing and composing HTML.
Home-page: https://github.com/SamDudley/neat-html
License: MIT
Keywords: html
Author: Sam Dudley
Author-email: dudley.co.uk@gmail.com
Requires-Python: >=3.10,<4.0
Classifier: License :: OSI Approved :: MIT License
Classifier: Programming Language :: Python :: 3
Classifier: Programming Language :: Python :: 3.10
Classifier: Programming Language :: Python :: 3.11
Classifier: Programming Language :: Python :: 3.12
Classifier: Topic :: Text Processing :: Markup :: HTML
Project-URL: Repository, https://github.com/SamDudley/neat-html
